lora_e32.py
lora_e32_constants.py
lora_e32_operation_constant.py
ebyte_lora_e32-0.0.4.dist-info/LICENSE.md
ebyte_lora_e32-0.0.4.dist-info/METADATA
ebyte_lora_e32-0.0.4.dist-info/WHEEL
ebyte_lora_e32-0.0.4.dist-info/top_level.txt
ebyte_lora_e32-0.0.4.dist-info/RECORD
